run_concurrently.py
run_concurrently-0.2.5.dist-info/METADATA
run_concurrently-0.2.5.dist-info/WHEEL
run_concurrently-0.2.5.dist-info/entry_points.txt
run_concurrently-0.2.5.dist-info/top_level.txt
run_concurrently-0.2.5.dist-info/RECORD
