Metadata-Version: 2.4
Name: run-concurrently
Version: 0.2.5
Summary: Zero dependency library to run multiple processes concurrently
Author: Eelke van den Bos
License-Expression: MIT
Project-URL: Homepage, https://github.com/eelkevdbos/run-concurrently
Project-URL: Source, https://github.com/eelkevdbos/run-concurrently
Project-URL: Issues, https://github.com/eelkevdbos/run-concurrently/issues
Classifier: Environment :: Console
Classifier: Intended Audience :: Developers
Classifier: Operating System :: Microsoft :: Windows
Classifier: Operating System :: POSIX
Classifier: Programming Language :: Python :: 3
Classifier: Programming Language :: Python :: 3.9
Classifier: Programming Language :: Python :: 3.10
Classifier: Programming Language :: Python :: 3.11
Classifier: Programming Language :: Python :: 3.12
Classifier: Programming Language :: Python :: 3.13
Requires-Python: >=3.9
